argguard/__init__.py
argguard/argguard.py
tests/__init__.py
tests/argguard_test.py
argguard-0.0.1.dist-info/LICENSE
argguard-0.0.1.dist-info/METADATA
argguard-0.0.1.dist-info/WHEEL
argguard-0.0.1.dist-info/top_level.txt
argguard-0.0.1.dist-info/RECORD
