Metadata-Version: 2.1
Name: argguard
Version: 0.0.1
Summary: Utility class to assert class arguments
Home-page: https://github.com/gcascio/arg-guard
Author: Giovanni Cascio
Author-email: giovanni@maternavis.com
License: UNKNOWN
Platform: UNKNOWN
Classifier: Programming Language :: Python :: 3
Classifier: License :: OSI Approved :: MIT License
Classifier: Operating System :: OS Independent
Requires-Python: >=3.7
License-File: LICENSE
